typst_fillable/__init__.py
typst_fillable/extractor.py
typst_fillable/merger.py
typst_fillable/models.py
typst_fillable/overlay.py
typst_fillable/typst/capture_field.typ
typst_fillable-0.0.1.dist-info/METADATA
typst_fillable-0.0.1.dist-info/WHEEL
typst_fillable-0.0.1.dist-info/licenses/LICENSE
typst_fillable-0.0.1.dist-info/RECORD
