Metadata-Version: 2.4
Name: typst-fillable
Version: 0.0.1
Summary: Add interactive form fields to Typst-generated PDFs
Project-URL: Homepage, https://github.com/carpe-diem/typst-fillable
Project-URL: Documentation, https://github.com/carpe-diem/typst-fillable#readme
Project-URL: Repository, https://github.com/carpe-diem/typst-fillable
Project-URL: Issues, https://github.com/carpe-diem/typst-fillable/issues
Author-email: Alberto Paparelli <carpedev@gmail.com>
License-Expression: MIT
License-File: LICENSE
Keywords: acroform,fillable,forms,pdf,reportlab,typst
Classifier: Development Status :: 3 - Alpha
Classifier: Intended Audience :: Developers
Classifier: License :: OSI Approved :: MIT License
Classifier: Programming Language :: Python :: 3
Classifier: Programming Language :: Python :: 3.10
Classifier: Programming Language :: Python :: 3.11
Classifier: Programming Language :: Python :: 3.12
Classifier: Topic :: Multimedia :: Graphics :: Graphics Conversion
Classifier: Topic :: Text Processing :: Markup
Requires-Python: >=3.10
Requires-Dist: pydantic>=2.0.0
Requires-Dist: pypdf>=4.0.0
Requires-Dist: reportlab>=4.0.0
Requires-Dist: typst>=0.12.0
Provides-Extra: dev
Requires-Dist: build>=1.0.0; extra == 'dev'
Requires-Dist: mypy>=1.0.0; extra == 'dev'
Requires-Dist: pytest-cov>=4.0.0; extra == 'dev'
Requires-Dist: pytest>=8.0.0; extra == 'dev'
Requires-Dist: ruff>=0.1.0; extra == 'dev'
Requires-Dist: twine>=5.0.0; extra == 'dev'
